{
    "blogDatas":[{
        "id":1,
        "name":"Get it Hurry with Budget",
        "date":"20 Dec, 2017",
        "oldPrice":"$30.00",
        "newPrice":"$20.00",
        "url":"assets/img/blog/1.jpg",
        "linkRouter":"...",
        "introduce":"Lorem ipsum dolor sit amet, consectetur adipiscing elit. Nam fringilla augue nec est tristique auctor. Morbi ornare lectus quis justo gravida semper. Nulla tellus mi, vulputate adipiscing cursus eu, suscipit id nulla."
    },{
        "id":2,
        "name":"Get it Hurry with Budget",
        "date":"20 Dec, 2017",
        "oldPrice":"$15.00",
        "newPrice":"$70.00",
        "url":"assets/img/blog/2.jpg",
        "linkRouter":"...",
        "introduce":"Lorem ipsum dolor sit consectetur adipisicing elit, sed do eiusmod tempor inquaerat.Lorem ipsum dolor sit consectetur adipisicing elit, sed do eiusmod tempor inquaerat."
    },{
        "id":3,
        "name":"Get it Hurry with Budget",
        "date":"20 Dec, 2017",
        "oldPrice":"$20.00",
        "newPrice":"$80.00",
        "url":"assets/img/blog/1.jpg",
        "linkRouter":"...",
        "introduce":"Lorem ipsum dolor tempor incididunt ut labore et dolore magna aliqua. Ut enim ad minim veniam, quis nostrud exerc tation ullamco labori ut aliquip ex ea commodo consequat."
    },{
        "id":4,
        "name":"Get it Hurry with Budget",
        "date":"20 Dec, 2017",
        "oldPrice":"$40.00",
        "newPrice":"$80.00",
        "url":"assets/img/blog/4.jpg",
        "linkRouter":"...",
        "introduce":"Lorem ipsum dolor tempor incididunt ut labore et dolore magna aliqua. Ut enim ad minim veniam, quis nostrud exerc tation ullamco labori ut aliquip ex ea commodo consequat."
    },{
        "id":5,
        "name":"Get it Hurry with Budget",
        "date":"20 Dec, 2017",
        "oldPrice":"$40.00",
        "newPrice":"$80.00",
        "url":"assets/img/blog/5.jpg",
        "linkRouter":"...",
        "introduce":"Lorem ipsum dolor tempor incididunt ut labore et dolore magna aliqua. Ut enim ad minim veniam, quis nostrud exerc tation ullamco labori ut aliquip ex ea commodo consequat."
    }]
}