{
    "productDatas":[{
        "id":1,
        "name":"Sun Skin",
        "smallName":"kajol & eyeliner",
        "hasOldPrice":true,
        "oldPrice":"$30.00",
        "newPrice":"$20.00",
        "url":"assets/img/product-tab/1.jpg",
        "linkRouter":"...",
        "sale":true,
        "new":false,
        "introduce":"Lorem ipsum dolor sit amet, consectetur adipiscing elit. Nam fringilla augue nec est tristique auctor. Donec non est at libero vulputate rutrum. Morbi ornare lectus quis justo gravida semper. Nulla tellus mi, vulputate adipiscing cursus eu, suscipit id nulla."
    },{
        "id":2,
        "name":"Double site Mirror",
        "smallName":"Blashan Brush",
        "oldPrice":"$15.00",
        "hasOldPrice":false,
        "newPrice":"$70.00",
        "url":"assets/img/product-tab/2.jpg",
        "linkRouter":"...",
        "sale":false,
        "new":true,
        "introduce":"Lorem ipsum dolor tempor incididunt ut labore et dolore magna aliqua. Ut enim ad minim veniam, quis nostrud exerc tation ullamco labori ut aliquip ex ea commodo consequat."
    },{
        "id":3,
        "name":"Punch Clipkajol & eyeliner",
        "smallName":"kajol & eyeliner",
        "oldPrice":"$20.00",
        "newPrice":"$80.00",
        "url":"assets/img/product-tab/3.jpg",
        "linkRouter":"...",
        "sale":false,
        "new":false,
        "introduce":"Lorem ipsum dolor tempor incididunt ut labore et dolore magna aliqua. Ut enim ad minim veniam, quis nostrud exerc tation ullamco labori ut aliquip ex ea commodo consequat."
    },{
        "id":4,
        "name":"Beauty BrushBlashan Brush",
        "smallName":"Blashan Brush",
        "oldPrice":"$40.00",
        "hasOldPrice":false,
        "newPrice":"$80.00",
        "url":"assets/img/product-tab/4.jpg",
        "linkRouter":"...",
        "sale":false,
        "new":false,
        "introduce":"Lorem ipsum dolor tempor incididunt ut labore et dolore magna aliqua. Ut enim ad minim veniam, quis nostrud exerc tation ullamco labori ut aliquip ex ea commodo consequat."
    },{
        "id":5,
        "name":"Beauty Brushkajol & eyeliner",
        "smallName":"kajol & eyeliner",
        "oldPrice":"$40.00",
        "hasOldPrice":false,
        "newPrice":"$80.00",
        "url":"assets/img/product-tab/5.jpg",
        "linkRouter":"...",
        "sale":false,
        "new":false,
        "introduce":"Lorem ipsum dolor tempor incididunt ut labore et dolore magna aliqua. Ut enim ad minim veniam, quis nostrud exerc tation ullamco labori ut aliquip ex ea commodo consequat."
    },{
        "id":6,
        "name":"Roberto Cavalli",
       "smallName":"Blashan Brush",
        "oldPrice":"$40.00",
        "hasOldPrice":false,
        "newPrice":"$80.00",
        "url":"assets/img/product-tab/6.jpg",
        "linkRouter":"...",
        "sale":false,
        "new":false,
        "introduce":"Lorem ipsum dolor tempor incididunt ut labore et dolore magna aliqua. Ut enim ad minim veniam, quis nostrud exerc tation ullamco labori ut aliquip ex ea commodo consequat."
    },{
        "id":7,
        "name":"Roberto Cavalli",
       "smallName":"Blashan Brush",
        "oldPrice":"$40.00",
        "hasOldPrice":false,
        "newPrice":"$80.00",
        "url":"assets/img/product-tab/6.jpg",
        "linkRouter":"...",
        "sale":false,
        "new":false,
        "introduce":"Lorem ipsum dolor tempor incididunt ut labore et dolore magna aliqua. Ut enim ad minim veniam, quis nostrud exerc tation ullamco labori ut aliquip ex ea commodo consequat."
    },{
        "id":8,
        "name":"Roberto Cavalli",
       "smallName":"Blashan Brush",
        "oldPrice":"$40.00",
        "hasOldPrice":false,
        "newPrice":"$80.00",
        "url":"assets/img/product-tab/6.jpg",
        "linkRouter":"...",
        "sale":false,
        "new":false,
        "introduce":"Lorem ipsum dolor tempor incididunt ut labore et dolore magna aliqua. Ut enim ad minim veniam, quis nostrud exerc tation ullamco labori ut aliquip ex ea commodo consequat."
    },{
        "id":9,
        "name":"Roberto Cavalli",
       "smallName":"Blashan Brush",
        "oldPrice":"$40.00",
        "hasOldPrice":false,
        "newPrice":"$80.00",
        "url":"assets/img/product-tab/6.jpg",
        "linkRouter":"...",
        "sale":false,
        "new":false,
        "introduce":"Lorem ipsum dolor tempor incididunt ut labore et dolore magna aliqua. Ut enim ad minim veniam, quis nostrud exerc tation ullamco labori ut aliquip ex ea commodo consequat."
    },{
        "id":10,
        "name":"Roberto Cavalli",
       "smallName":"Blashan Brush",
        "oldPrice":"$40.00",
        "hasOldPrice":false,
        "newPrice":"$80.00",
        "url":"assets/img/product-tab/6.jpg",
        "linkRouter":"...",
        "sale":false,
        "new":false,
        "introduce":"Lorem ipsum dolor tempor incididunt ut labore et dolore magna aliqua. Ut enim ad minim veniam, quis nostrud exerc tation ullamco labori ut aliquip ex ea commodo consequat."
    },{
        "id":11,
        "name":"Roberto Cavalli",
       "smallName":"Blashan Brush",
        "oldPrice":"$40.00",
        "hasOldPrice":false,
        "newPrice":"$80.00",
        "url":"assets/img/product-tab/6.jpg",
        "linkRouter":"...",
        "sale":false,
        "new":false,
        "introduce":"Lorem ipsum dolor tempor incididunt ut labore et dolore magna aliqua. Ut enim ad minim veniam, quis nostrud exerc tation ullamco labori ut aliquip ex ea commodo consequat."
    },{
        "id":12,
        "name":"Roberto Cavalli",
       "smallName":"Blashan Brush",
        "oldPrice":"$40.00",
        "hasOldPrice":false,
        "newPrice":"$80.00",
        "url":"assets/img/product-tab/6.jpg",
        "linkRouter":"...",
        "sale":false,
        "new":false,
        "introduce":"Lorem ipsum dolor tempor incididunt ut labore et dolore magna aliqua. Ut enim ad minim veniam, quis nostrud exerc tation ullamco labori ut aliquip ex ea commodo consequat."
    },{
        "id":13,
        "name":"Sun Skin",
        "smallName":"kajol & eyeliner",
        "hasOldPrice":true,
        "oldPrice":"$30.00",
        "newPrice":"$20.00",
        "url":"assets/img/product-tab/1.jpg",
        "linkRouter":"...",
        "sale":true,
        "new":false,
        "introduce":"Lorem ipsum dolor sit amet, consectetur adipiscing elit. Nam fringilla augue nec est tristique auctor. Donec non est at libero vulputate rutrum. Morbi ornare lectus quis justo gravida semper. Nulla tellus mi, vulputate adipiscing cursus eu, suscipit id nulla."
    },{
        "id":14,
        "name":"Double site Mirror",
        "smallName":"Blashan Brush",
        "oldPrice":"$15.00",
        "hasOldPrice":false,
        "newPrice":"$70.00",
        "url":"assets/img/product-tab/2.jpg",
        "linkRouter":"...",
        "sale":false,
        "new":true,
        "introduce":"Lorem ipsum dolor tempor incididunt ut labore et dolore magna aliqua. Ut enim ad minim veniam, quis nostrud exerc tation ullamco labori ut aliquip ex ea commodo consequat."
    },{
        "id":15,
        "name":"Punch Clipkajol & eyeliner",
        "smallName":"kajol & eyeliner",
        "oldPrice":"$20.00",
        "newPrice":"$80.00",
        "url":"assets/img/product-tab/3.jpg",
        "linkRouter":"...",
        "sale":false,
        "new":false,
        "introduce":"Lorem ipsum dolor tempor incididunt ut labore et dolore magna aliqua. Ut enim ad minim veniam, quis nostrud exerc tation ullamco labori ut aliquip ex ea commodo consequat."
    },{
        "id":16,
        "name":"Beauty BrushBlashan Brush",
        "smallName":"Blashan Brush",
        "oldPrice":"$40.00",
        "hasOldPrice":false,
        "newPrice":"$80.00",
        "url":"assets/img/product-tab/4.jpg",
        "linkRouter":"...",
        "sale":false,
        "new":false,
        "introduce":"Lorem ipsum dolor tempor incididunt ut labore et dolore magna aliqua. Ut enim ad minim veniam, quis nostrud exerc tation ullamco labori ut aliquip ex ea commodo consequat."
    },{
        "id":17,
        "name":"Beauty Brushkajol & eyeliner",
        "smallName":"kajol & eyeliner",
        "oldPrice":"$40.00",
        "hasOldPrice":false,
        "newPrice":"$80.00",
        "url":"assets/img/product-tab/5.jpg",
        "linkRouter":"...",
        "sale":false,
        "new":false,
        "introduce":"Lorem ipsum dolor tempor incididunt ut labore et dolore magna aliqua. Ut enim ad minim veniam, quis nostrud exerc tation ullamco labori ut aliquip ex ea commodo consequat."
    },{
        "id":18,
        "name":"Roberto Cavalli",
       "smallName":"Blashan Brush",
        "oldPrice":"$40.00",
        "hasOldPrice":false,
        "newPrice":"$80.00",
        "url":"assets/img/product-tab/6.jpg",
        "linkRouter":"...",
        "sale":false,
        "new":false,
        "introduce":"Lorem ipsum dolor tempor incididunt ut labore et dolore magna aliqua. Ut enim ad minim veniam, quis nostrud exerc tation ullamco labori ut aliquip ex ea commodo consequat."
    },{
        "id":19,
        "name":"Roberto Cavalli",
       "smallName":"Blashan Brush",
        "oldPrice":"$40.00",
        "hasOldPrice":false,
        "newPrice":"$80.00",
        "url":"assets/img/product-tab/6.jpg",
        "linkRouter":"...",
        "sale":false,
        "new":false,
        "introduce":"Lorem ipsum dolor tempor incididunt ut labore et dolore magna aliqua. Ut enim ad minim veniam, quis nostrud exerc tation ullamco labori ut aliquip ex ea commodo consequat."
    },{
        "id":20,
        "name":"Roberto Cavalli",
       "smallName":"Blashan Brush",
        "oldPrice":"$40.00",
        "hasOldPrice":false,
        "newPrice":"$80.00",
        "url":"assets/img/product-tab/6.jpg",
        "linkRouter":"...",
        "sale":false,
        "new":false,
        "introduce":"Lorem ipsum dolor tempor incididunt ut labore et dolore magna aliqua. Ut enim ad minim veniam, quis nostrud exerc tation ullamco labori ut aliquip ex ea commodo consequat."
    },{
        "id":21,
        "name":"Roberto Cavalli",
       "smallName":"Blashan Brush",
        "oldPrice":"$40.00",
        "hasOldPrice":false,
        "newPrice":"$80.00",
        "url":"assets/img/product-tab/6.jpg",
        "linkRouter":"...",
        "sale":false,
        "new":false,
        "introduce":"Lorem ipsum dolor tempor incididunt ut labore et dolore magna aliqua. Ut enim ad minim veniam, quis nostrud exerc tation ullamco labori ut aliquip ex ea commodo consequat."
    },{
        "id":22,
        "name":"Roberto Cavalli",
       "smallName":"Blashan Brush",
        "oldPrice":"$40.00",
        "hasOldPrice":false,
        "newPrice":"$80.00",
        "url":"assets/img/product-tab/6.jpg",
        "linkRouter":"...",
        "sale":false,
        "new":false,
        "introduce":"Lorem ipsum dolor tempor incididunt ut labore et dolore magna aliqua. Ut enim ad minim veniam, quis nostrud exerc tation ullamco labori ut aliquip ex ea commodo consequat."
    },{
        "id":23,
        "name":"Roberto Cavalli",
       "smallName":"Blashan Brush",
        "oldPrice":"$40.00",
        "hasOldPrice":false,
        "newPrice":"$80.00",
        "url":"assets/img/product-tab/6.jpg",
        "linkRouter":"...",
        "sale":false,
        "new":false,
        "introduce":"Lorem ipsum dolor tempor incididunt ut labore et dolore magna aliqua. Ut enim ad minim veniam, quis nostrud exerc tation ullamco labori ut aliquip ex ea commodo consequat."
    },{
        "id":24,
        "name":"Roberto Cavalli",
       "smallName":"Blashan Brush",
        "oldPrice":"$40.00",
        "hasOldPrice":false,
        "newPrice":"$80.00",
        "url":"assets/img/product-tab/6.jpg",
        "linkRouter":"...",
        "sale":false,
        "new":false,
        "introduce":"Lorem ipsum dolor tempor incididunt ut labore et dolore magna aliqua. Ut enim ad minim veniam, quis nostrud exerc tation ullamco labori ut aliquip ex ea commodo consequat."
    }]
}